{
    "HorseMod.HorseSaddle_Crude": "Sedlo pro koně (provizorní)",
    "HorseMod.HorseSaddle_Black": "Sedlo pro koně (černé)",
    "HorseMod.HorseSaddle_CowHolstein": "Sedlo pro koně (Holstein)",
    "HorseMod.HorseSaddle_CowSimmental": "Sedlo pro koně (Simmental)",
    "HorseMod.HorseSaddle_White": "Sedlo pro koně (bílé)",
    "HorseMod.HorseSaddle_Landrace": "Sedlo pro koně (Landrace)",
    "HorseMod.HorseSaddle_AmericanPaintOvero": "Sedlo pro koně (Overo)",
    "HorseMod.HorseSaddle_AmericanPaintTobiano": "Sedlo pro koně (Tobiano)",
    "HorseMod.HorseSaddle_AmericanQuarterBlueRoan": "Sedlo pro koně (Blue Roan)",
    "HorseMod.HorseSaddle_AmericanQuarterPalomino": "Sedlo pro koně (Palomino)",
    "HorseMod.HorseSaddle_AppaloosaGrullaBlanket": "Sedlo pro koně (Grulla Blanket)",
    "HorseMod.HorseSaddle_AppaloosaLeopard": "Sedlo pro koně (Leopard)",
    "HorseMod.HorseSaddle_ThoroughbredBay": "Sedlo pro koně (Bay)",
    "HorseMod.HorseSaddle_ThoroughbredFleaBittenGrey": "Sedlo pro koně (Flea-Bitten Grey)",
    "HorseMod.HorseSaddle_Western": "Sedlo pro koně (Western)",
    "HorseMod.HorseSaddlebagsContainer": "Brašny pro koně",
    "HorseMod.HorseSaddlebags_Crude": "Brašny pro koně (provizorní)",
    "HorseMod.HorseSaddlebags_Black": "Brašny pro koně (černé)",
    "HorseMod.HorseSaddlebags_CowHolstein": "Brašny pro koně (Holstein)",
    "HorseMod.HorseSaddlebags_CowSimmental": "Brašny pro koně (Simmental)",
    "HorseMod.HorseSaddlebags_White": "Brašny pro koně (bílé)",
    "HorseMod.HorseSaddlebags_Landrace": "Brašny pro koně (Landrace)",
    "HorseMod.HorseSaddlebags_AmericanPaintOvero": "Brašny pro koně (Overo)",
    "HorseMod.HorseSaddlebags_AmericanPaintTobiano": "Brašny pro koně (Tobiano)",
    "HorseMod.HorseSaddlebags_AmericanQuarterBlueRoan": "Brašny pro koně (Blue Roan)",
    "HorseMod.HorseSaddlebags_AmericanQuarterPalomino": "Brašny pro koně (Palomino)",
    "HorseMod.HorseSaddlebags_AppaloosaGrullaBlanket": "Brašny pro koně (Grulla Blanket)",
    "HorseMod.HorseSaddlebags_AppaloosaLeopard": "Brašny pro koně (Leopard)",
    "HorseMod.HorseSaddlebags_ThoroughbredBay": "Brašny pro koně (Bay)",
    "HorseMod.HorseSaddlebags_ThoroughbredFleaBittenGrey": "Brašny pro koně (Flea-Bitten Grey)",
    "HorseMod.HorseReins_Crude": "Otěže pro koně (provizorní)",
    "HorseMod.HorseReins_Brown": "Otěže pro koně (hnědé)",
    "HorseMod.HorseReins_Black": "Otěže pro koně (černé)",
    "HorseMod.HorseReins_White": "Otěže pro koně (bílé)",
    "HorseMod.Foal_Head_AmericanPaintOvero": "Hlava hříběte American Paint",
    "HorseMod.Mare_Head_AmericanPaintOvero": "Hlava klisny American Paint",
    "HorseMod.Stallion_Head_AmericanPaintOvero": "Hlava hřebce American Paint",
    "HorseMod.Foal_Head_AmericanPaintTobiano": "Hlava hříběte American Paint",
    "HorseMod.Mare_Head_AmericanPaintTobiano": "Hlava klisny American Paint",
    "HorseMod.Stallion_Head_AmericanPaintTobiano": "Hlava hřebce American Paint",
    "HorseMod.Foal_Head_AmericanQuarterBlueRoan": "Hlava hříběte American Quarter",
    "HorseMod.Mare_Head_AmericanQuarterBlueRoan": "Hlava klisny American Quarter",
    "HorseMod.Stallion_Head_AmericanQuarterBlueRoan": "Hlava hřebce American Quarter",
    "HorseMod.Foal_Head_AmericanQuarterPalomino": "Hlava hříběte American Quarter",
    "HorseMod.Mare_Head_AmericanQuarterPalomino": "Hlava klisny American Quarter",
    "HorseMod.Stallion_Head_AmericanQuarterPalomino": "Hlava hřebce American Quarter",
    "HorseMod.Foal_Head_AppaloosaGrullaBlanket": "Hlava hříběte Appaloosa",
    "HorseMod.Mare_Head_AppaloosaGrullaBlanket": "Hlava klisny Appaloosa",
    "HorseMod.Stallion_Head_AppaloosaGrullaBlanket": "Hlava hřebce Appaloosa",
    "HorseMod.Foal_Head_AppaloosaLeopard": "Hlava hříběte Appaloosa",
    "HorseMod.Mare_Head_AppaloosaLeopard": "Hlava klisny Appaloosa",
    "HorseMod.Stallion_Head_AppaloosaLeopard": "Hlava hřebce Appaloosa",
    "HorseMod.Foal_Head_ThoroughbredBay": "Hlava hříběte plnokrevníka",
    "HorseMod.Mare_Head_ThoroughbredBay": "Hlava klisny plnokrevníka",
    "HorseMod.Stallion_Head_ThoroughbredBay": "Hlava hřebce plnokrevníka",
    "HorseMod.Foal_Head_ThoroughbredFleaBittenGrey": "Hlava hříběte plnokrevníka",
    "HorseMod.Mare_Head_ThoroughbredFleaBittenGrey": "Hlava klisny plnokrevníka",
    "HorseMod.Stallion_Head_ThoroughbredFleaBittenGrey": "Hlava hřebce plnokrevníka",
    "HorseMod.Horse_Skull": "Koňská lebka",
    "HorseMod.Horse_Steak": "Koňský steak",
    "HorseMod.Horse_Loin": "Koňská pečeně",
    "HorseMod.Horse_Hoof": "Koňské kopyto",
    "HorseMod.PotHorseGlue": "Hrnec s koňským klihem",
    "HorseMod.PotForgedHorseGlue": "Kovaný hrnec s koňským klihem",
    "HorseMod.HorseGlue": "Koňský klíh",
    "HorseMod.HorseLeather_AmericanPaintOvero_Full": "Kůže American Paint Overo (nezpracovaná)",
    "HorseMod.HorseLeather_AmericanPaintOvero_Fur": "Kůže American Paint Overo (se srstí)",
    "HorseMod.HorseLeather_AmericanPaintOvero_Fur_Tan_Wet": "Kůže American Paint Overo (se srstí, mokrá)",
    "HorseMod.HorseLeather_AmericanPaintOvero_Fur_Tan": "Kůže American Paint Overo (se srstí)",
    "HorseMod.HorseLeather_AmericanPaintOvero_Fur_Tan_Medium": "Kůže American Paint Overo (se srstí, polovina)",
    "HorseMod.HorseLeather_AmericanPaintOvero_Fur_Tan_Small": "Kůže American Paint Overo (se srstí, čtvrtina)",
    "HorseMod.HorseLeather_AmericanPaintTobiano_Full": "Kůže American Paint Tobiano (nezpracovaná)",
    "HorseMod.HorseLeather_AmericanPaintTobiano_Fur": "Kůže American Paint Tobiano (se srstí)",
    "HorseMod.HorseLeather_AmericanPaintTobiano_Fur_Tan_Wet": "Kůže American Paint Tobiano (se srstí, mokrá)",
    "HorseMod.HorseLeather_AmericanPaintTobiano_Fur_Tan": "Kůže American Paint Tobiano (se srstí)",
    "HorseMod.HorseLeather_AmericanPaintTobiano_Fur_Tan_Medium": "Kůže American Paint Tobiano (se srstí, polovina)",
    "HorseMod.HorseLeather_AmericanPaintTobiano_Fur_Tan_Small": "Kůže American Paint Tobiano (se srstí, čtvrtina)",
    "HorseMod.HorseLeather_AmericanQuarterBlueRoan_Full": "American Quarter Blue Roan Hide (nezpracovaná)",
    "HorseMod.HorseLeather_AmericanQuarterBlueRoan_Fur": "American Quarter Blue Roan Hide (se srstí)",
    "HorseMod.HorseLeather_AmericanQuarterBlueRoan_Fur_Tan_Wet": "American Quarter Blue Roan Leather (se srstí, mokrá)",
    "HorseMod.HorseLeather_AmericanQuarterBlueRoan_Fur_Tan": "American Quarter Blue Roan Leather (se srstí)",
    "HorseMod.HorseLeather_AmericanQuarterBlueRoan_Fur_Tan_Medium": "American Quarter Blue Roan Leather Half (Furred)",
    "HorseMod.HorseLeather_AmericanQuarterBlueRoan_Fur_Tan_Small": "American Quarter Blue Roan Leather Quarter (Furred)",
    "HorseMod.HorseLeather_AmericanQuarterPalomino_Full": "American Quarter Palomino Hide (Unprocessed)",
    "HorseMod.HorseLeather_AmericanQuarterPalomino_Fur": "American Quarter Palomino Hide (Furred)",
    "HorseMod.HorseLeather_AmericanQuarterPalomino_Fur_Tan_Wet": "American Quarter Palomino Leather (Furred, Wet)",
    "HorseMod.HorseLeather_AmericanQuarterPalomino_Fur_Tan": "American Quarter Palomino Leather (Furred)",
    "HorseMod.HorseLeather_AmericanQuarterPalomino_Fur_Tan_Medium": "American Quarter Palomino Leather Half (Furred)",
    "HorseMod.HorseLeather_AmericanQuarterPalomino_Fur_Tan_Small": "American Quarter Palomino Leather Quarter (Furred)",
    "HorseMod.HorseLeather_AppaloosaGrullaBlanket_Full": "Appaloosa Grulla Blanket Hide (Unprocessed)",
    "HorseMod.HorseLeather_AppaloosaGrullaBlanket_Fur": "Appaloosa Grulla Blanket Hide (Furred)",
    "HorseMod.HorseLeather_AppaloosaGrullaBlanket_Fur_Tan_Wet": "Appaloosa Grulla Blanket Leather (Furred, Wet)",
    "HorseMod.HorseLeather_AppaloosaGrullaBlanket_Fur_Tan": "Appaloosa Grulla Blanket Leather (Furred)",
    "HorseMod.HorseLeather_AppaloosaGrullaBlanket_Fur_Tan_Medium": "Appaloosa Grulla Blanket Leather Half (Furred)",
    "HorseMod.HorseLeather_AppaloosaGrullaBlanket_Fur_Tan_Small": "Appaloosa Grulla Blanket Leather Quarter (Furred)",
    "HorseMod.HorseLeather_AppaloosaLeopard_Full": "Appaloosa Leopard Hide (Unprocessed)",
    "HorseMod.HorseLeather_AppaloosaLeopard_Fur": "Appaloosa Leopard Hide (Furred)",
    "HorseMod.HorseLeather_AppaloosaLeopard_Fur_Tan_Wet": "Appaloosa Leopard Leather (Furred, Wet)",
    "HorseMod.HorseLeather_AppaloosaLeopard_Fur_Tan": "Appaloosa Leopard Leather (Furred)",
    "HorseMod.HorseLeather_AppaloosaLeopard_Fur_Tan_Medium": "Appaloosa Leopard Leather Half (Furred)",
    "HorseMod.HorseLeather_AppaloosaLeopard_Fur_Tan_Small": "Appaloosa Leopard Leather Quarter (Furred)",
    "HorseMod.HorseLeather_ThoroughbredBay_Full": "Thoroughbred Bay Hide (Unprocessed)",
    "HorseMod.HorseLeather_ThoroughbredBay_Fur": "Thoroughbred Bay Hide (Furred)",
    "HorseMod.HorseLeather_ThoroughbredBay_Fur_Tan_Wet": "Thoroughbred Bay Leather (Furred, Wet)",
    "HorseMod.HorseLeather_ThoroughbredBay_Fur_Tan": "Thoroughbred Bay Leather (Furred)",
    "HorseMod.HorseLeather_ThoroughbredBay_Fur_Tan_Medium": "Thoroughbred Bay Leather Half (Furred)",
    "HorseMod.HorseLeather_ThoroughbredBay_Fur_Tan_Small": "Thoroughbred Bay Leather Quarter (Furred)",
    "HorseMod.HorseLeather_ThoroughbredFleaBittenGrey_Full": "Thoroughbred Flea-Bitten Grey Hide (Unprocessed)",
    "HorseMod.HorseLeather_ThoroughbredFleaBittenGrey_Fur": "Thoroughbred Flea-Bitten Grey Hide (Furred)",
    "HorseMod.HorseLeather_ThoroughbredFleaBittenGrey_Fur_Tan_Wet": "Thoroughbred Flea-Bitten Grey Leather (Furred, Wet)",
    "HorseMod.HorseLeather_ThoroughbredFleaBittenGrey_Fur_Tan": "Thoroughbred Flea-Bitten Grey Leather (Furred)",
    "HorseMod.HorseLeather_ThoroughbredFleaBittenGrey_Fur_Tan_Medium": "Thoroughbred Flea-Bitten Grey Leather Half (Furred)",
    "HorseMod.HorseLeather_ThoroughbredFleaBittenGrey_Fur_Tan_Small": "Thoroughbred Flea-Bitten Grey Leather Quarter (Furred)",
    "HorseMod.FoalLeather_AmericanPaintOvero_Full": "Hříběcí kůže American Paint Overo (nezpracovaná)",
    "HorseMod.FoalLeather_AmericanPaintOvero_Fur": "Hříběcí kůže American Paint Overo (se srstí)",
    "HorseMod.FoalLeather_AmericanPaintOvero_Fur_Tan_Wet": "Hříběcí kůže American Paint Overo (se srstí, mokrá)",
    "HorseMod.FoalLeather_AmericanPaintOvero_Fur_Tan": "Hříběcí kůže American Paint Overo (se srstí)",
    "HorseMod.FoalLeather_AmericanPaintOvero_Fur_Tan_Small": "Hříběcí kůže American Paint Overo (se srstí, polovina)",
    "HorseMod.FoalLeather_AmericanPaintTobiano_Full": "Hříběcí kůže American Paint Tobiano (nezpracovaná)",
    "HorseMod.FoalLeather_AmericanPaintTobiano_Fur": "Hříběcí kůže American Paint Tobiano (se srstí)",
    "HorseMod.FoalLeather_AmericanPaintTobiano_Fur_Tan_Wet": "Hříběcí kůže American Paint Tobiano (se srstí, mokrá)",
    "HorseMod.FoalLeather_AmericanPaintTobiano_Fur_Tan": "Hříběcí kůže American Paint Tobiano (se srstí)",
    "HorseMod.FoalLeather_AmericanPaintTobiano_Fur_Tan_Small": "Hříběcí kůže American Paint Tobiano (se srstí, polovina)",
    "HorseMod.FoalLeather_AmericanQuarterBlueRoan_Full": "Hříběcí kůže American Quarter Blue Roan (nezpracovaná)",
    "HorseMod.FoalLeather_AmericanQuarterBlueRoan_Fur": "Hříběcí kůže American Quarter Blue Roan (se srstí)",
    "HorseMod.FoalLeather_AmericanQuarterBlueRoan_Fur_Tan_Wet": "Hříběcí kůže American Quarter Blue Roan (se srstí, mokrá)",
    "HorseMod.FoalLeather_AmericanQuarterBlueRoan_Fur_Tan": "Hříběcí kůže American Quarter Blue Roan (se srstí)",
    "HorseMod.FoalLeather_AmericanQuarterBlueRoan_Fur_Tan_Small": "Hříběcí kůže American Quarter Blue Roan (se srstí, polovina)",
    "HorseMod.FoalLeather_AmericanQuarterPalomino_Full": "Hříběcí kůže American Quarter Palomino (nezpracovaná)",
    "HorseMod.FoalLeather_AmericanQuarterPalomino_Fur": "Hříběcí kůže American Quarter Palomino (se srstí)",
    "HorseMod.FoalLeather_AmericanQuarterPalomino_Fur_Tan_Wet": "Hříběcí kůže American Quarter Palomino (se srstí, mokrá)",
    "HorseMod.FoalLeather_AmericanQuarterPalomino_Fur_Tan": "Hříběcí kůže American Quarter Palomino (se srstí)",
    "HorseMod.FoalLeather_AmericanQuarterPalomino_Fur_Tan_Small": "Hříběcí kůže American Quarter Palomino (se srstí, polovina)",
    "HorseMod.FoalLeather_AppaloosaGrullaBlanket_Full": "Hříběcí kůže Appaloosa Grulla Blanket (nezpracovaná)",
    "HorseMod.FoalLeather_AppaloosaGrullaBlanket_Fur": "Hříběcí kůže Appaloosa Grulla Blanket (se srstí)",
    "HorseMod.FoalLeather_AppaloosaGrullaBlanket_Fur_Tan_Wet": "Hříběcí kůže Appaloosa Grulla Blanket (se srstí, mokrá)",
    "HorseMod.FoalLeather_AppaloosaGrullaBlanket_Fur_Tan": "Hříběcí kůže Appaloosa Grulla Blanket (se srstí)",
    "HorseMod.FoalLeather_AppaloosaGrullaBlanket_Fur_Tan_Small": "Hříběcí kůže Appaloosa Grulla Blanket (se srstí, polovina)",
    "HorseMod.FoalLeather_AppaloosaLeopard_Full": "Hříběcí kůže Appaloosa Leopard (nezpracovaná)",
    "HorseMod.FoalLeather_AppaloosaLeopard_Fur": "Hříběcí kůže Appaloosa Leopard (se srstí)",
    "HorseMod.FoalLeather_AppaloosaLeopard_Fur_Tan_Wet": "Hříběcí kůže Appaloosa Leopard (se srstí, mokrá)",
    "HorseMod.FoalLeather_AppaloosaLeopard_Fur_Tan": "Hříběcí kůže Appaloosa Leopard (se srstí)",
    "HorseMod.FoalLeather_AppaloosaLeopard_Fur_Tan_Small": "Hříběcí kůže Appaloosa Leopard (se srstí, polovina)",
    "HorseMod.FoalLeather_ThoroughbredBay_Full": "Hříběcí kůže Thoroughbred Bay (nezpracovaná)",
    "HorseMod.FoalLeather_ThoroughbredBay_Fur": "Hříběcí kůže Thoroughbred Bay (se srstí)",
    "HorseMod.FoalLeather_ThoroughbredBay_Fur_Tan_Wet": "Hříběcí kůže Thoroughbred Bay (se srstí, mokrá)",
    "HorseMod.FoalLeather_ThoroughbredBay_Fur_Tan": "Hříběcí kůže Thoroughbred Bay (se srstí)",
    "HorseMod.FoalLeather_ThoroughbredBay_Fur_Tan_Small": "Hříběcí kůže Thoroughbred Bay (se srstí, polovina)",
    "HorseMod.FoalLeather_ThoroughbredFleaBittenGrey_Full": "Hříběcí kůže Thoroughbred Flea-Bitten Grey (nezpracovaná)",
    "HorseMod.FoalLeather_ThoroughbredFleaBittenGrey_Fur": "Hříběcí kůže Thoroughbred Flea-Bitten Grey (se srstí)",
    "HorseMod.FoalLeather_ThoroughbredFleaBittenGrey_Fur_Tan_Wet": "Hříběcí kůže Thoroughbred Flea-Bitten Grey (se srstí, mokrá)",
    "HorseMod.FoalLeather_ThoroughbredFleaBittenGrey_Fur_Tan": "Hříběcí kůže Thoroughbred Flea-Bitten Grey (se srstí)",
    "HorseMod.FoalLeather_ThoroughbredFleaBittenGrey_Fur_Tan_Small": "Hříběcí kůže Thoroughbred Flea-Bitten Grey (se srstí, polovina)"
}
